<?xml version="1.0" encoding="UTF-8"?>
<REQUEST USERID="" UNITID="" PASSWORD="" xmlns="http://Request.SubmitAiP.Epsom.Omiga.vertex.co.uk" xmlns:OmigaAiPData="http://OmigaAiPData.Epsom.Omiga.vertex.co.uk" xmlns:msgdt="http://msgtypes.Epsom.Omiga.vertex.co.uk" xmlns:xsi="http://www.w3.org/2001/XMLSchema-instance" xsi:schemaLocation="http://Request.SubmitAiP.Epsom.Omiga.vertex.co.uk
C:\ProjectEpson\SubmitAiPRequest.xsd">
	<APPLICATION>
		<OmigaAiPData:APPLICATIONFACTFIND PURCHASEPRICEORESTIMATEDVALUE="0" TYPEOFAPPLICATION="0" NATUREOFLOAN="0" PRODUCTSCHEME="0" SELFCERTIND="true">
			<OmigaAiPData:QUOTATION>
				<OmigaAiPData:MORTGAGESUBQUOTE AMOUNTREQUESTED="0">
					<OmigaAiPData:LOANCOMPONENT MORTGAGEPRODUCTCODE="0" FINALRATE="0"/>
				</OmigaAiPData:MORTGAGESUBQUOTE>
			</OmigaAiPData:QUOTATION>
			<OmigaAiPData:CUSTOMERROLE CUSTOMERROLETYPE="0" CUSTOMERORDER="0">
				<OmigaAiPData:CUSTOMER OTHERSYSTEMCUSTOMERNUMBER="">
					<OmigaAiPData:CUSTOMERVERSION TITLE="" FIRSTFORENAME="" SECONDFORENAME="" SURNAME="" DATEOFBIRTH="01/01/1965" GENDER="0" MARITALSTATUS="0">
						<OmigaAiPData:CUSTOMERADDRESS ADDRESSTYPE="0" DATEMOVEDIN="01/01/1990" NATUREOFOCCUPANCY="0" DATEMOVEDOUT="01/01/1990">
							<OmigaAiPData:ADDRESS BUILDINGORHOUSENAME="" BUILDINGORHOUSENUMBER="" FLATNUMBER="" STREET="" DISTRICT="" TOWN="" COUNTY="" COUNTRY="0" POSTCODE=""/>
						</OmigaAiPData:CUSTOMERADDRESS>
						<OmigaAiPData:CUSTOMERADDRESS ADDRESSTYPE="0" DATEMOVEDIN="01/01/1990" NATUREOFOCCUPANCY="0" DATEMOVEDOUT="01/01/1990">
							<OmigaAiPData:ADDRESS BUILDINGORHOUSENAME="" BUILDINGORHOUSENUMBER="" FLATNUMBER="" STREET="" DISTRICT="" TOWN="" COUNTY="" COUNTRY="0" POSTCODE=""/>
						</OmigaAiPData:CUSTOMERADDRESS>
						<OmigaAiPData:CUSTOMERADDRESS ADDRESSTYPE="0" DATEMOVEDIN="01/01/1990" NATUREOFOCCUPANCY="0" DATEMOVEDOUT="01/01/1990">
							<OmigaAiPData:ADDRESS BUILDINGORHOUSENAME="" BUILDINGORHOUSENUMBER="" FLATNUMBER="" STREET="" DISTRICT="" TOWN="" COUNTY="" COUNTRY="0" POSTCODE=""/>
						</OmigaAiPData:CUSTOMERADDRESS>
						<OmigaAiPData:EMPLOYMENT EMPLOYMENTSTATUS="0" DATESTARTEDORESTABLISHED="01/01/1990">
							<OmigaAiPData:EARNEDINCOME EARNEDINCOMEAMOUNT="0"/>
						</OmigaAiPData:EMPLOYMENT>
					</OmigaAiPData:CUSTOMERVERSION>
				</OmigaAiPData:CUSTOMER>
			</OmigaAiPData:CUSTOMERROLE>
		</OmigaAiPData:APPLICATIONFACTFIND>
		<OmigaAiPData:PACKAGER PACKAGERNUMBER="" PACKAGERAPPREFNUMBER="" PACKAGERINDIVIDUALNAME=""/>
	</APPLICATION>
</REQUEST>